<annotation>
	<folder>images</folder>
	<filename>112.jpg</filename>
	<path>D:\PycharmProjects\yolov5\VOCData\images\112.jpg</path>
	<source>
		<database>Unknown</database>
	</source>
	<size>
		<width>400</width>
		<height>225</height>
		<depth>3</depth>
	</size>
	<segmented>0</segmented>
	<object>
		<name>baggage</name>
		<pose>Unspecified</pose>
		<truncated>0</truncated>
		<difficult>0</difficult>
		<bndbox>
			<xmin>115</xmin>
			<ymin>9</ymin>
			<xmax>189</xmax>
			<ymax>56</ymax>
		</bndbox>
	</object>
	<object>
		<name>baggage</name>
		<pose>Unspecified</pose>
		<truncated>0</truncated>
		<difficult>0</difficult>
		<bndbox>
			<xmin>143</xmin>
			<ymin>90</ymin>
			<xmax>200</xmax>
			<ymax>156</ymax>
		</bndbox>
	</object>
	<object>
		<name>baggage</name>
		<pose>Unspecified</pose>
		<truncated>0</truncated>
		<difficult>0</difficult>
		<bndbox>
			<xmin>154</xmin>
			<ymin>151</ymin>
			<xmax>240</xmax>
			<ymax>212</ymax>
		</bndbox>
	</object>
</annotation>
